libro_core/__init__.py
libro_core/_version.py
libro_core/config.py
libro_core-0.1.6.dist-info/METADATA
libro_core-0.1.6.dist-info/WHEEL
libro_core-0.1.6.dist-info/RECORD
