Metadata-Version: 2.3
Name: libro-core
Version: 0.1.6
Summary: libro core
Author-email: sunshinesmilelk <ximo.lk66@gmail.com>, brokun <brokun0128@gmail.com>
Requires-Python: >=3.8.1
Requires-Dist: pyyaml>=6.0.2
